CHANGES.rst
MANIFEST.in
README.rst
setup.py
docs/LICENSE.GPL
docs/LICENSE.rst
rt/__init__.py
rt.ploneversions.egg-info/PKG-INFO
rt.ploneversions.egg-info/SOURCES.txt
rt.ploneversions.egg-info/dependency_links.txt
rt.ploneversions.egg-info/entry_points.txt
rt.ploneversions.egg-info/namespace_packages.txt
rt.ploneversions.egg-info/not-zip-safe
rt.ploneversions.egg-info/requires.txt
rt.ploneversions.egg-info/top_level.txt
rt/ploneversions/__init__.py
rt/ploneversions/ploneversions.py
rt/ploneversions/tests/__init__.py
rt/ploneversions/tests/test_parsing.py
rt/ploneversions/tests/mocks/main.cfg
rt/ploneversions/tests/mocks/sub1.cfg
rt/ploneversions/tests/mocks/sub2.cfg
rt/ploneversions/tests/mocks/subsub.cfg