Metadata-Version: 1.1
Name: rt.ploneversions
Version: 0.9.0
Summary: Retrieve information from dist.plone.org to safely and easily pin your egg versions
Home-page: http://www.redturtle.it/
Author: RedTurtle Technology
Author-email: sviluppolplone@redturtle.it
License: GPL
Platform: UNKNOWN
Classifier: Development Status :: 4 - Beta
Classifier: Intended Audience :: Developers
Classifier: License :: OSI Approved :: GNU General Public License (GPL)
Classifier: Programming Language :: Python :: 2.6
Classifier: Programming Language :: Python :: 2.7
Classifier: Programming Language :: Python
Classifier: Topic :: Software Development :: Libraries :: Python Modules
